rpaworkflow/__init__.py
rpaworkflow/context.py
rpaworkflow/exception.py
rpaworkflow/manager.py
rpaworkflow/node.py
rpaworkflow/drissionpage/__init__.py
rpaworkflow/drissionpage/workflow_context.py
rpaworkflow/drissionpage/nodes/__init__.py
rpaworkflow/drissionpage/nodes/base.py
rpaworkflow/drissionpage/nodes/check_element.py
rpaworkflow/drissionpage/nodes/click.py
rpaworkflow/drissionpage/nodes/close_page.py
rpaworkflow/drissionpage/nodes/connect_page.py
rpaworkflow/drissionpage/nodes/form.py
rpaworkflow/drissionpage/nodes/get_text.py
rpaworkflow/drissionpage/nodes/input_text.py
rpaworkflow/drissionpage/nodes/navigate.py
rpaworkflow/drissionpage/nodes/screenshot.py
rpaworkflow/drissionpage/nodes/scroll.py
rpaworkflow/drissionpage/nodes/wait.py
rpaworkflow/func/__init__.py
rpaworkflow/func/ctx.py
rpaworkflow/func/op.py
rpaworkflow/nodes/__init__.py
rpaworkflow/nodes/condition.py
rpaworkflow/nodes/delay.py
rpaworkflow/nodes/empty.py
rpaworkflow/nodes/error.py
rpaworkflow/nodes/lambda_.py
rpaworkflow/nodes/loop.py
rpaworkflow/nodes/wait_time.py
rpaworkflow/playwright/__init__.py
rpaworkflow/playwright/workflow_context.py
rpaworkflow/playwright/nodes/__init__.py
rpaworkflow/playwright/nodes/base.py
rpaworkflow/playwright/nodes/click.py
rpaworkflow/playwright/nodes/close_browser.py
rpaworkflow/playwright/nodes/connect_browser.py
rpaworkflow/playwright/nodes/element_check.py
rpaworkflow/playwright/nodes/get_text.py
rpaworkflow/playwright/nodes/input_text.py
rpaworkflow/playwright/nodes/navigate.py
rpaworkflow/playwright/nodes/screenshot.py
rpaworkflow/playwright/nodes/scroll.py
rpaworkflow/playwright/nodes/wait.py
rpaworkflow/selenium/__init__.py
rpaworkflow/selenium/workflow_context.py
rpaworkflow/selenium/nodes/__init__.py
rpaworkflow/selenium/nodes/base.py
rpaworkflow/selenium/nodes/check_element.py
rpaworkflow/selenium/nodes/click.py
rpaworkflow/selenium/nodes/close_browser.py
rpaworkflow/selenium/nodes/connect_browser.py
rpaworkflow/selenium/nodes/get_text.py
rpaworkflow-0.0.3.dist-info/METADATA
rpaworkflow-0.0.3.dist-info/WHEEL
rpaworkflow-0.0.3.dist-info/licenses/LICENSE
rpaworkflow-0.0.3.dist-info/RECORD
