Metadata-Version: 2.4
Name: rpaworkflow
Version: 0.0.3
Summary: RPA工作流框架，支持多种自动化工具的工作流管理和节点执行
Project-URL: Homepage, https://github.com/yourusername/rpaworkflow
Project-URL: Bug Tracker, https://github.com/yourusername/rpaworkflow/issues
Author-email: RPA Workflow Team <example@example.com>
License: MIT
License-File: LICENSE
Keywords: automation,playwright,rpa,selenium,uiautomator2,workflow
Classifier: Development Status :: 4 - Beta
Classifier: Intended Audience :: Developers
Classifier: License :: OSI Approved :: MIT License
Classifier: Programming Language :: Python :: 3
Classifier: Programming Language :: Python :: 3.11
Classifier: Topic :: Software Development :: Libraries :: Python Modules
Classifier: Topic :: Software Development :: Testing
Requires-Python: >=3.8
Requires-Dist: loguru
Provides-Extra: all
Requires-Dist: drissionpage>=4.0.0; extra == 'all'
Requires-Dist: playwright>=1.20.0; extra == 'all'
Requires-Dist: selenium>=4.0.0; extra == 'all'
Requires-Dist: uiautomator2>=2.16.0; extra == 'all'
Requires-Dist: undetected-chromedriver>=3.0.0; extra == 'all'
Provides-Extra: drissionpage
Requires-Dist: drissionpage>=4.0.0; extra == 'drissionpage'
Provides-Extra: playwright
Requires-Dist: playwright>=1.20.0; extra == 'playwright'
Provides-Extra: selenium
Requires-Dist: selenium>=4.0.0; extra == 'selenium'
Provides-Extra: uiautomator2
Requires-Dist: uiautomator2>=2.16.0; extra == 'uiautomator2'
Provides-Extra: undetected-chromedriver
Requires-Dist: undetected-chromedriver>=3.0.0; extra == 'undetected-chromedriver'
